Workbook

Sheet Revenue by Product Category
A3: Sum of Sales | B3: Column Labels | F3: Chiboodle sales grew 9.56% in 2015; Growth was driven primarily by product segments Drinks and Tacos
A4: Row Labels | B4: 2014 | C4: 2015 | D4: Grand Total
A5: Burritos | B5: 1.7240004e+09 | C5: 1.7104647e+09 | D5: 3.4344651e+09
A6: Drinks | B6: 6.3872664e+08 | C6: 9.6776295e+08 | D6: 1.6064896e+09
A7: Kids menu | B7: 3.4910505e+08 | C7: 3.6009784e+08 | D7: 7.0920289e+08
A8: Tacos | B8: 1.3964369e+09 | C8: 1.4628975e+09 | D8: 2.8593344e+09
A9: Grand Total | B9: 4.108269e+09 | C9: 4.501223e+09 | D9: 8.609492e+09
A14: Column1 | B14: 2014 | C14: 2015 | D14: YoY
A15: Burritos | B15: 1.7240004e+09 | C15: 1.7104647e+09 | D15: =(C15/Table1[[#This Row],[2014]])-1 -> -0.0078512943
A16: Drinks | B16: 6.3872664e+08 | C16: 9.6776295e+08 | D16: =(C16/Table1[[#This Row],[2014]])-1 -> 0.51514417
A17: Kids menu | B17: 3.4910505e+08 | C17: 3.6009784e+08 | D17: =(C17/Table1[[#This Row],[2014]])-1 -> 0.031488492
A18: Tacos | B18: 1.3964369e+09 | C18: 1.4628975e+09 | D18: =(C18/Table1[[#This Row],[2014]])-1 -> 0.047592939
A19: Grand Total | B19: 4.108269e+09 | C19: 4.501223e+09 | D19: =(C19/Table1[[#This Row],[2014]])-1 -> 0.09564953

Sheet SLIDE2(old)
A3: Sum of Sales | B3: Column Labels
A4: Row Labels | B4: New | C4: Old | D4: Grand Total
A5: 2014 | B5: 4.0304912e+08 | C5: 3.7052199e+09 | D5: 4.108269e+09
A6: 2015 | B6: 3.6443409e+08 | C6: 4.1367889e+09 | D6: 4.501223e+09
A7: Grand Total | B7: 7.6748321e+08 | C7: 7.8420088e+09 | D7: 8.609492e+09
B11: New | C11: Old
A12: 2014 | B12: 4.0304912e+08 | C12: 3.7052199e+09
A13: 2015 | B13: 3.6443409e+08 | C13: 4.1367889e+09

Sheet New vs Existing store sales
A3: Sum of Sales | B3: Column Labels
A4: Row Labels | B4: 2014 | C4: 2015 | D4: Grand Total
A5: Existing | B5: 4.108269e+09 | C5: 4.1367889e+09 | D5: 8.2450579e+09
A6: New | C6: 3.6443409e+08 | D6: 3.6443409e+08
A7: Grand Total | B7: 4.108269e+09 | C7: 4.501223e+09 | D7: 8.609492e+09
B12: 2014 | C12: 2015
A13: Existing | B13: 4.108269e+09 | C13: 4.1367889e+09 | D13: =C13/(C13+C14) -> 0.91903665 | E13: =(C13/B13-1) -> 0.0069420748
A14: New | C14: 3.6443409e+08 | D14: =C14/(C13+C14) -> 0.080963349
A15: Total | B15: =SUM(B13,B14) -> 4.108269e+09 | C15: =SUM(C13,C14) -> 4.501223e+09 | D15: =(C15/B15)-1 -> 0.09564953

Sheet No of new locations by year
A3: Row Labels | B3: Count of Store_ID | G3: Count of Store_ID
A4: 1994 | B4: 1 | F4: 1994 | G4: 1
A5: 1995 | B5: 1 | F5: 1995 | G5: 1
A6: 1996 | B6: 5 | F6: 1996 | G6: 5
A7: 1997 | B7: 13 | F7: 1997 | G7: 13
A8: 1998 | B8: 22 | F8: 1998 | G8: 22
A9: 1999 | B9: 58 | F9: 1999 | G9: 58
A10: 2000 | B10: 69 | F10: 2000 | G10: 69
A11: 2001 | B11: 115 | F11: 2001 | G11: 115
A12: 2002 | B12: 116 | F12: 2002 | G12: 116
A13: 2003 | B13: 130 | F13: 2003 | G13: 130
A14: 2004 | B14: 131 | F14: 2004 | G14: 131
A15: 2005 | B15: 145 | F15: 2005 | G15: 145
... A25: 2015 | B25: 200 | F25: 2015 | G25: 200
A26: Grand Total | B26: 2443 | F26: 2016 | G26: ='C. New locations planned'!F$3 -> 153
F27: 2017 | G27: ='C. New locations planned'!G$3 -> 101
F28: 2018 | G28: ='C. New locations planned'!H$3 -> 72
F29: 2019 | G29: ='C. New locations planned'!I$3 -> 62

Sheet Business as usual forecast
B2: 2014 | C2: 2015 | D2: 2016 | E2: 2017 | F2: 2018 | G2: 2019
A4: No of Stores | B4: 2243 | C4: ='C. New locations planned'!E$4 -> 2443 | D4: ='C. New locations planned'!F$4 -> 2596 | E4: ='C. New locations planned'!G$4 -> 2697 | F4: ='C. New locations planned'!H$4 -> 2769 | G4: ='C. New locations planned'!I$4 -> 2831
A6: Revenue per store(all products) | B6: =SUM(B9,B14,B19,B24) -> 1831595.6 | C6: =SUM(C9,C14,C19,C24) -> 1842498.2 | D6: =SUM(D9,D14,D19,D24) -> 1754223.7 | E6: =SUM(E9,E14,E19,E24) -> 1672847.2 | F6: =SUM(F9,F14,F19,F24) -> 1597819.6 | G6: =SUM(G9,G14,G19,G24) -> 1528637.8
A7: Yoy change | B7: - | C7: =(C6/B6)-1 -> 0.005952475 | D7: =C7 -> 0.005952475 | E7: =D7 -> 0.005952475 | F7: =E7 -> 0.005952475 | G7: =F7 -> 0.005952475 | H7: (not sure this is required)
A9: Burritos (revenue per store) | B9: =J15 -> 768613.63 | C9: =K15 -> 700149.3 | D9: =C9*(1+D10) -> 637783.44 | E9: =D9*(1+E10) -> 580972.82 | F9: =E9*(1+F10) -> 529222.61 | G9: =F9*(1+G10) -> 482082.06
A10: Yoy change | B10: - | C10: =(C9/B9)-1 -> -0.089075093 | D10: =C10 -> -0.089075093 | E10: =D10 -> -0.089075093 | F10: =E10 -> -0.089075093 | G10: =F10 -> -0.089075093
A11: Burritos Total Revenue | B11: =B9*B4 -> 1.7240004e+09 | C11: =C9*C4 -> 1.7104647e+09 | D11: =D9*D4 -> 1.6556858e+09 | E11: =E9*E4 -> 1.5668837e+09 | F11: =F9*F4 -> 1.4654174e+09 | G11: =G9*G4 -> 1.3647743e+09
A12: Yoy change | B12: - | C12: =(C11/B11)-1 -> -0.0078512943 | D12: =(D11/C11)-1 -> -0.032025764 | E12: =(E11/D11)-1 -> -0.053634641 | F12: =(F11/E11)-1 -> -0.064756742 | G12: =(G11/F11)-1 -> -0.068678797
A14: Tacos (revenue per store) | B14: =J18 -> 622575.54 | C14: =K18 -> 598811.9 | D14: =C14*(1+D15) -> 575955.32 | E14: =D14*(1+E15) -> 553971.17 | F14: =E14*(1+F15) -> 532826.15 | G14: =F14*(1+G15) -> 512488.23 | I14: Row Labels | J14: 2014 | K14: 2015
A15: yoy change | B15: - | C15: =(C14/B14)-1 -> -0.038169889 | D15: =C15 -> -0.038169889 | E15: =D15 -> -0.038169889 | F15: =E15 -> -0.038169889 | G15: =F15 -> -0.038169889 | I15: Burritos | J15: 768613.63 | K15: 700149.3
A16: Tacos Total Revenue | B16: =B14*B4 -> 1.3964369e+09 | C16: =C14*C4 -> 1.4628975e+09 | D16: =D14*D4 -> 1.49518e+09 | E16: =E14*E4 -> 1.4940602e+09 | F16: =F14*F4 -> 1.4753956e+09 | G16: =G14*G4 -> 1.4508542e+09 | I16: Drinks | J16: 284764.44 | K16: 396137.1
A17: yoy change | B17: - | C17: =(C16/B16)-1 -> 0.047592939 | D17: =(D16/C16)-1 -> 0.022067527 | E17: =(E16/D16)-1 -> -0.00074891742 | F17: =(F16/E16)-1 -> -0.012492555 | G17: =(G16/F16)-1 -> -0.016633786 | I17: Kids menu | J17: 155642.02 | K17: 147399.85
I18: Tacos | J18: 622575.54 | K18: 598811.9
A19: Kids meal (revenue per store) | B19: =J17 -> 155642.02 | C19: =K17 -> 147399.85 | D19: =C19*(1+D20) -> 139594.16 | E19: =D19*(1+E20) -> 132201.82 | F19: =E19*(1+F20) -> 125200.95 | G19: =F19*(1+G20) -> 118570.82
A20: Yoy change | B20: - | C20: =(C19/B19)-1 -> -0.05295592 | D20: =C20 -> -0.05295592 | E20: =D20 -> -0.05295592 | F20: =E20 -> -0.05295592 | G20: =F20 -> -0.05295592
A21: Kids Meal Total Revenue | B21: =B19*B4 -> 3.4910505e+08 | C21: =C19*C4 -> 3.6009784e+08 | D21: =D19*D4 -> 3.6238643e+08 | E21: =E19*E4 -> 3.5654831e+08 | F21: =F19*F4 -> 3.4668144e+08 | G21: =G19*G4 -> 3.3567399e+08
A22: Yoy change | B22: - | C22: =(C21/B21)-1 -> 0.031488492 | D22: =(D21/C21)-1 -> 0.006355478 | E22: =(E21/D21)-1 -> -0.016110214 | F22: =(F21/E21)-1 -> -0.027673319 | G22: =(G21/F21)-1 -> -0.031750888
A24: Drinks (revenue per store) | B24: =J16 -> 284764.44 | C24: =K16 -> 396137.1 | D24: =C24*(1+D25) -> 400890.75 | E24: =D24*(1+E25) -> 405701.44 | F24: =E24*(1+F25) -> 410569.86 | G24: =F24*(1+G25) -> 415496.69
A25: Yoy change | B25: - | C25: =(C24/B24)-1 -> 0.39110453 | D25: 0.012 | E25: =D25 -> 0.012 | F25: =E25 -> 0.012 | G25: =F25 -> 0.012
A26: Drinks Total Revenue | B26: =B24*B4 -> 6.3872664e+08 | C26: =C24*C4 -> 9.6776295e+08 | D26: =D24*D4 -> 1.0407124e+09 | E26: =E24*E4 -> 1.0941768e+09 | F26: =F24*F4 -> 1.1368679e+09 | G26: =G24*G4 -> 1.1762711e+09
A27: Yoy change | B27: - | C27: =(C26/B26)-1 -> 0.51514417 | D27: =(D26/C26)-1 -> 0.075379451 | E27: =(E26/D26)-1 -> 0.051372881 | F27: =(F26/E26)-1 -> 0.039016685 | G27: =(G26/F26)-1 -> 0.034659444
A29: Chiboodle Total Revenue | B29: =B6*B4 -> 4.108269e+09 | C29: =C6*C4 -> 4.501223e+09 | D29: =D6*D4 -> 4.5539646e+09 | E29: =E6*E4 -> 4.511669e+09 | F29: =F6*F4 -> 4.4243624e+09 | G29: =G6*G4 -> 4.3275736e+09
A30: Revenue growth % (year on year) | B30: - | C30: =(C29/B29)-1 -> 0.09564953 | D30: =(D29/C29)-1 -> 0.011717176 | E30: =(E29/D29)-1 -> -0.0092876453 | F30: =(F29/E29)-1 -> -0.019351295 | G30: =(G29/F29)-1 -> -0.021876317
B34: Column1 | C34: 2015 | D34: 2016 | E34: 2017 | F34: 2018 | G34: 2019
B35: No of Stores | C35: 2443 | D35: 2596 | E35: 2697 | F35: 2769 | G35: 2831
B36: Revenue per store(all products) | C36: 1842498.2 | D36: 1754223.7 | E36: 1672847.2 | F36: 1597819.6 | G36: 1528637.8
B37: Burritos (revenue per store) | C37: 700149.3 | D37: 637783.44 | E37: 580972.82 | F37: 529222.61 | G37: 482082.06
B38: Tacos (revenue per store) | C38: 598811.9 | D38: 575955.32 | E38: 553971.17 | F38: 532826.15 | G38: 512488.23
B39: Kids meal (revenue per store) | C39: 147399.85 | D39: 139594.16 | E39: 132201.82 | F39: 125200.95 | G39: 118570.82
B40: Drinks (revenue per store) | C40: 396137.1 | D40: 400890.75 | E40: 405701.44 | F40: 410569.86 | G40: 415496.69
B41: Chiboodle Total Revenue | C41: 4.501223e+09 | D41: 4.5539646e+09 | E41: 4.511669e+09 | F41: 4.4243624e+09 | G41: 4.3275736e+09
B42: Revenue growth % (year on year) | C42: 0.09564953 | D42: 0.011717176 | E42: -0.0092876453 | F42: -0.019351295 | G42: -0.021876317

Sheet Revenue forecast with Salads 
B2: 2014 | C2: 2015 | D2: 2016 | E2: 2017 | F2: 2018 | G2: 2019
A4: No of Stores | B4: 2243 | C4: ='C. New locations planned'!E$4 -> 2443 | D4: ='C. New locations planned'!F$4 -> 2596 | E4: ='C. New locations planned'!G$4 -> 2697 | F4: ='C. New locations planned'!H$4 -> 2769 | G4: ='C. New locations planned'!I$4 -> 2831
A5: No of stores adopting salads | D5: =D4*'G. Adoption curves'!H4 -> 432.66667 | E5: =E4*'G. Adoption curves'!H5 -> 746.17 | F5: =F4*'G. Adoption curves'!H6 -> 1513.72 | G5: =G4*'G. Adoption curves'!H7 -> 2274.2367 | I5: Product | J5: Average Price
I6: Burritos | J6: 9.85
A7: Revenue per store(all products) | B7: =SUM(B10,B14,B18,B22) -> 1831595.6 | C7: =SUM(C10,C14,C18,C22) -> 1842498.2 | D7: =SUM(D10,D14,D18,D22) -> 1754223.7 | E7: =SUM(E10,E14,E18,E22) -> 1672847.2 | F7: =SUM(F10,F14,F18,F22) -> 1597819.6 | G7: =SUM(G10,G14,G18,G22) -> 1528637.8 | I7: Tacos | J7: 5.83
A8: Yoy change | B8: - | C8: =(C7/B7)-1 -> 0.005952475 | D8: =C8 -> 0.005952475 | E8: =D8 -> 0.005952475 | F8: =E8 -> 0.005952475 | G8: =F8 -> 0.005952475 | I8: Kids menu | J8: 5.29
I9: Drinks | J9: 3.37
A10: Burritos (revenue per store) | B10: =J17 -> 768613.63 | C10: =K17 -> 700149.3 | D10: =C10*(1+D11) -> 637783.44 | E10: =D10*(1+E11) -> 580972.82 | F10: =E10*(1+F11) -> 529222.61 | G10: =F10*(1+G11) -> 482082.06 | I10: Salads | J10: ='E. Competitor salad prices'!$E$13 -> 8.4439074
A11: Yoy change | B11: - | C11: =(C10/B10)-1 -> -0.089075093 | D11: =C11 -> -0.089075093 | E11: =D11 -> -0.089075093 | F11: =E11 -> -0.089075093 | G11: =F11 -> -0.089075093
A12: No of units sold per store | B12: =B10/$J$6 -> 78031.841 | C12: =C10/$J$6 -> 71081.147 | D12: =D10/$J$6 -> 64749.587 | E12: =E10/$J$6 -> 58982.012 | F12: =F10/$J$6 -> 53728.184 | G12: =G10/$J$6 -> 48942.341
A14: Tacos (revenue per store) | B14: =J20 -> 622575.54 | C14: =K20 -> 598811.9 | D14: =C14*(1+D15) -> 575955.32 | E14: =D14*(1+E15) -> 553971.17 | F14: =E14*(1+F15) -> 532826.15 | G14: =F14*(1+G15) -> 512488.23
A15: yoy change | B15: - | C15: =(C14/B14)-1 -> -0.038169889 | D15: =C15 -> -0.038169889 | E15: =D15 -> -0.038169889 | F15: =E15 -> -0.038169889 | G15: =F15 -> -0.038169889
A16: No of units sold per store | B16: =B14/$J$7 -> 106788.26 | C16: =C14/$J$7 -> 102712.16 | D16: =D14/$J$7 -> 98791.65 | E16: =E14/$J$7 -> 95020.783 | F16: =F14/$J$7 -> 91393.851 | G16: =G14/$J$7 -> 87905.358 | I16: Row Labels | J16: 2014 | K16: 2015
I17: Burritos | J17: 768613.63 | K17: 700149.3
A18: Kids meal (revenue per store) | B18: =J19 -> 155642.02 | C18: =K19 -> 147399.85 | D18: =C18*(1+D19) -> 139594.16 | E18: =D18*(1+E19) -> 132201.82 | F18: =E18*(1+F19) -> 125200.95 | G18: =F18*(1+G19) -> 118570.82 | I18: Drinks | J18: 284764.44 | K18: 396137.1
A19: Yoy change | B19: - | C19: =(C18/B18)-1 -> -0.05295592 | D19: =C19 -> -0.05295592 | E19: =D19 -> -0.05295592 | F19: =E19 -> -0.05295592 | G19: =F19 -> -0.05295592 | I19: Kids menu | J19: 155642.02 | K19: 147399.85
A20: No of units sold per store | B20: =B18/$J$8 -> 29421.932 | C20: =C18/$J$8 -> 27863.866 | D20: =D18/$J$8 -> 26388.31 | E20: =E18/$J$8 -> 24990.892 | F20: =F18/$J$8 -> 23667.477 | G20: =G18/$J$8 -> 22414.144 | I20: Tacos | J20: 622575.54 | K20: 598811.9
A22: Drinks (revenue per store) | B22: =J18 -> 284764.44 | C22: =K18 -> 396137.1 | D22: =C22*(1+D23) -> 400890.75 | E22: =D22*(1+E23) -> 405701.44 | F22: =E22*(1+F23) -> 410569.86 | G22: =F22*(1+G23) -> 415496.69
A23: Yoy change | B23: - | C23: =(C22/B22)-1 -> 0.39110453 | D23: 0.012 | E23: =D23 -> 0.012 | F23: =E23 -> 0.012 | G23: =F23 -> 0.012
A24: No of units sold per store | B24: =B22/$J$9 -> 84499.834 | C24: =C22/$J$9 -> 117548.1 | D24: =D22/$J$9 -> 118958.68 | E24: =E22/$J$9 -> 120386.18 | F24: =F22/$J$9 -> 121830.82 | G24: =G22/$J$9 -> 123292.79
A26: Salads (revenue per store) | D26: =D28*$J10 -> 235602.3 | E26: =E28*$J10 -> 224382.83 | F26: =F28*$J10 -> 213789.94 | G26: =G28*$J10 -> 203782.05
A27: Yoy change | D27: - | E27: =(E26/D26)-1 -> -0.047620352 | F27: =(F26/E26)-1 -> -0.047208997 | G27: =(G26/F26)-1 -> -0.046811814
A28: No of units sold per store | D28: =(D12*'F. Survey'!$E$8)+(D16*'F. Survey'!$F$9) -> 27902.046 | E28: =(E12*'F. Survey'!$E$8)+('Revenue forecast with Salads '!E16*'F. Survey'!$F$9) -> 26573.341 | F28: =(F12*'F. Survey'!$E$8)+('Revenue forecast with Salads '!F16*'F. Survey'!$F$9) -> 25318.84 | G28: =(G12*'F. Survey'!$E$8)+('Revenue forecast with Salads '!G16*'F. Survey'!$F$9) -> 24133.619
A30: Chiboodle Total Revenue | B30: =B7*B4 -> 4.108269e+09 | C30: =C7*C4 -> 4.501223e+09 | D30: =(D7*D4)-('F. Survey'!$E$8*D10*D5)+(D26*D5) -> 4.6338261e+09 | E30: =(E7*E4)-('F. Survey'!$E$8*E10*E5)+(E26*E5) -> 4.6444164e+09 | F30: =(F7*F4)-('F. Survey'!$E$8*F10*F5)+(F26*F5) -> 4.6838929e+09 | G30: =(G7*G4)-('F. Survey'!$E$8*G10*G5)+(G26*G5) -> 4.7033127e+09
A31: Revenue growth % (year on year) | B31: - | C31: =(C30/B30)-1 -> 0.09564953 | D31: =(D30/C30)-1 -> 0.029459343 | E31: =(E30/D30)-1 -> 0.0022854378 | F31: =(F30/E30)-1 -> 0.0084997783 | G31: =(G30/F30)-1 -> 0.0041460882
B34: Column1 | C34: 2015 | D34: 2016 | E34: 2017 | F34: 2018 | G34: 2019
B35: No of Stores | C35: ='C. New locations planned'!E$4 -> 2443 | D35: ='C. New locations planned'!F$4 -> 2596 | E35: ='C. New locations planned'!G$4 -> 2697 | F35: ='C. New locations planned'!H$4 -> 2769 | G35: ='C. New locations planned'!I$4 -> 2831
B36: Revenue per store(all products) | C36: 1842498.2 | D36: 1754223.7 | E36: 1672847.2 | F36: 1597819.6 | G36: 1528637.8
B37: Burritos (revenue per store) | C37: 700149.3 | D37: 637783.44 | E37: 580972.82 | F37: 529222.61 | G37: 482082.06
B38: Tacos (revenue per store) | C38: 598811.9 | D38: 575955.32 | E38: 553971.17 | F38: 532826.15 | G38: 512488.23
B39: Kids meal (revenue per store) | C39: 147399.85 | D39: 139594.16 | E39: 132201.82 | F39: 125200.95 | G39: 118570.82
B40: Drinks (revenue per store) | C40: 396137.1 | D40: 400890.75 | E40: 405701.44 | F40: 410569.86 | G40: 415496.69
B41: Salads (revenue per store) | D41: 235602.3 | E41: 224382.83 | F41: 213789.94 | G41: 203782.05
B42: Chiboodle Total Revenue | C42: 4.501223e+09 | D42: 4.6338261e+09 | E42: 4.6444164e+09 | F42: 4.6838929e+09 | G42: 4.7033127e+09
B43: Revenue growth % (year on year) | C43: 0.09564953 | D43: 0.029459343 | E43: 0.0022854378 | F43: 0.0084997783 | G43: 0.0041460882

Sheet Forecast with high salad prices
B2: 2014 | C2: 2015 | D2: 2016 | E2: 2017 | F2: 2018 | G2: 2019
A4: No of Stores | B4: 2243 | C4: ='C. New locations planned'!E$4 -> 2443 | D4: ='C. New locations planned'!F$4 -> 2596 | E4: ='C. New locations planned'!G$4 -> 2697 | F4: ='C. New locations planned'!H$4 -> 2769 | G4: ='C. New locations planned'!I$4 -> 2831
A5: No of stores adopting salads | D5: =D4*'G. Adoption curves'!H4 -> 432.66667 | E5: =E4*'G. Adoption curves'!H5 -> 746.17 | F5: =F4*'G. Adoption curves'!H6 -> 1513.72 | G5: =G4*'G. Adoption curves'!H7 -> 2274.2367 | I5: Product | J5: Average Price
I6: Burritos | J6: 9.85
A7: Revenue per store(all products) | B7: =SUM(B10,B14,B18,B22) -> 1831595.6 | C7: =SUM(C10,C14,C18,C22) -> 1842498.2 | D7: =SUM(D10,D14,D18,D22) -> 1754223.7 | E7: =SUM(E10,E14,E18,E22) -> 1672847.2 | F7: =SUM(F10,F14,F18,F22) -> 1597819.6 | G7: =SUM(G10,G14,G18,G22) -> 1528637.8 | I7: Tacos | J7: 5.83
A8: Yoy change | B8: - | C8: =(C7/B7)-1 -> 0.005952475 | D8: =C8 -> 0.005952475 | E8: =D8 -> 0.005952475 | F8: =E8 -> 0.005952475 | G8: =F8 -> 0.005952475 | I8: Kids menu | J8: 5.29
I9: Drinks | J9: 3.37
A10: Burritos (revenue per store) | B10: =J17 -> 768613.63 | C10: =K17 -> 700149.3 | D10: =C10*(1+D11) -> 637783.44 | E10: =D10*(1+E11) -> 580972.82 | F10: =E10*(1+F11) -> 529222.61 | G10: =F10*(1+G11) -> 482082.06 | I10: Salads | J10: ='E. Competitor salad prices'!$E$14 -> 10.384588
A11: Yoy change | B11: - | C11: =(C10/B10)-1 -> -0.089075093 | D11: =C11 -> -0.089075093 | E11: =D11 -> -0.089075093 | F11: =E11 -> -0.089075093 | G11: =F11 -> -0.089075093
A12: No of units sold per store | B12: =B10/$J$6 -> 78031.841 | C12: =C10/$J$6 -> 71081.147 | D12: =D10/$J$6 -> 64749.587 | E12: =E10/$J$6 -> 58982.012 | F12: =F10/$J$6 -> 53728.184 | G12: =G10/$J$6 -> 48942.341
A14: Tacos (revenue per store) | B14: =J20 -> 622575.54 | C14: =K20 -> 598811.9 | D14: =C14*(1+D15) -> 575955.32 | E14: =D14*(1+E15) -> 553971.17 | F14: =E14*(1+F15) -> 532826.15 | G14: =F14*(1+G15) -> 512488.23
A15: yoy change | B15: - | C15: =(C14/B14)-1 -> -0.038169889 | D15: =C15 -> -0.038169889 | E15: =D15 -> -0.038169889 | F15: =E15 -> -0.038169889 | G15: =F15 -> -0.038169889
A16: No of units sold per store | B16: =B14/$J$7 -> 106788.26 | C16: =C14/$J$7 -> 102712.16 | D16: =D14/$J$7 -> 98791.65 | E16: =E14/$J$7 -> 95020.783 | F16: =F14/$J$7 -> 91393.851 | G16: =G14/$J$7 -> 87905.358 | I16: Row Labels | J16: 2014 | K16: 2015
I17: Burritos | J17: 768613.63 | K17: 700149.3
A18: Kids meal (revenue per store) | B18: =J19 -> 155642.02 | C18: =K19 -> 147399.85 | D18: =C18*(1+D19) -> 139594.16 | E18: =D18*(1+E19) -> 132201.82 | F18: =E18*(1+F19) -> 125200.95 | G18: =F18*(1+G19) -> 118570.82 | I18: Drinks | J18: 284764.44 | K18: 396137.1
A19: Yoy change | B19: - | C19: =(C18/B18)-1 -> -0.05295592 | D19: =C19 -> -0.05295592 | E19: =D19 -> -0.05295592 | F19: =E19 -> -0.05295592 | G19: =F19 -> -0.05295592 | I19: Kids menu | J19: 155642.02 | K19: 147399.85
A20: No of units sold per store | B20: =B18/$J$8 -> 29421.932 | C20: =C18/$J$8 -> 27863.866 | D20: =D18/$J$8 -> 26388.31 | E20: =E18/$J$8 -> 24990.892 | F20: =F18/$J$8 -> 23667.477 | G20: =G18/$J$8 -> 22414.144 | I20: Tacos | J20: 622575.54 | K20: 598811.9
A22: Drinks (revenue per store) | B22: =J18 -> 284764.44 | C22: =K18 -> 396137.1 | D22: =C22*(1+D23) -> 400890.75 | E22: =D22*(1+E23) -> 405701.44 | F22: =E22*(1+F23) -> 410569.86 | G22: =F22*(1+G23) -> 415496.69
A23: Yoy change | B23: - | C23: =(C22/B22)-1 -> 0.39110453 | D23: 0.012 | E23: =D23 -> 0.012 | F23: =E23 -> 0.012 | G23: =F23 -> 0.012
A24: No of units sold per store | B24: =B22/$J$9 -> 84499.834 | C24: =C22/$J$9 -> 117548.1 | D24: =D22/$J$9 -> 118958.68 | E24: =E22/$J$9 -> 120386.18 | F24: =F22/$J$9 -> 121830.82 | G24: =G22/$J$9 -> 123292.79
A26: Salads (revenue per store) | D26: =D28*$J10 -> 289751.26 | E26: =E28*$J10 -> 275953.2 | F26: =F28*$J10 -> 262925.72 | G26: =G28*$J10 -> 250617.69
A27: Yoy change | D27: - | E27: =(E26/D26)-1 -> -0.047620352 | F27: =(F26/E26)-1 -> -0.047208997 | G27: =(G26/F26)-1 -> -0.046811814
A28: No of units sold per store | D28: =(D12*'F. Survey'!$E$8)+(D16*'F. Survey'!$F$9) -> 27902.046 | E28: =(E12*'F. Survey'!$E$8)+('Revenue forecast with Salads '!E16*'F. Survey'!$F$9) -> 26573.341 | F28: =(F12*'F. Survey'!$E$8)+('Revenue forecast with Salads '!F16*'F. Survey'!$F$9) -> 25318.84 | G28: =(G12*'F. Survey'!$E$8)+('Revenue forecast with Salads '!G16*'F. Survey'!$F$9) -> 24133.619
A30: Chiboodle Total Revenue | B30: =B7*B4 -> 4.108269e+09 | C30: =C7*C4 -> 4.501223e+09 | D30: =(D7*D4)-('F. Survey'!$E$8*D10*D5)+(D26*D5) -> 4.6572545e+09 | E30: =(E7*E4)-('F. Survey'!$E$8*E10*E5)+(E26*E5) -> 4.6828967e+09 | F30: =(F7*F4)-('F. Survey'!$E$8*F10*F5)+(F26*F5) -> 4.7582707e+09 | G30: =(G7*G4)-('F. Survey'!$E$8*G10*G5)+(G26*G5) -> 4.8098281e+09
A31: Revenue growth % (year on year) | B31: - | C31: =(C30/B30)-1 -> 0.09564953 | D31: =(D30/C30)-1 -> 0.034664251 | E31: =(E30/D30)-1 -> 0.0055058472 | F31: =(F30/E30)-1 -> 0.016095607 | G31: =(G30/F30)-1 -> 0.010835315

Sheet Analysis
A1: Column1 | B1: 2015 | C1: 2016 | D1: 2017 | E1: 2018 | F1: 2019
A2: Business as usual | B2: ='Business as usual forecast'!C$29 -> 4.501223e+09 | C2: ='Business as usual forecast'!D$29 -> 4.5539646e+09 | D2: ='Business as usual forecast'!E$29 -> 4.511669e+09 | E2: ='Business as usual forecast'!F$29 -> 4.4243624e+09 | F2: ='Business as usual forecast'!G$29 -> 4.3275736e+09
A3: Project crunch scenario 1 | B3: ='Revenue forecast with Salads '!C$30 -> 4.501223e+09 | C3: ='Revenue forecast with Salads '!D$30 -> 4.6338261e+09 | D3: ='Revenue forecast with Salads '!E$30 -> 4.6444164e+09 | E3: ='Revenue forecast with Salads '!F$30 -> 4.6838929e+09 | F3: ='Revenue forecast with Salads '!G$30 -> 4.7033127e+09
A4: Project crunch scenario 2 | B4: ='Forecast with high salad prices'!C$30 -> 4.501223e+09 | C4: ='Forecast with high salad prices'!D$30 -> 4.6572545e+09 | D4: ='Forecast with high salad prices'!E$30 -> 4.6828967e+09 | E4: ='Forecast with high salad prices'!F$30 -> 4.7582707e+09 | F4: ='Forecast with high salad prices'!G$30 -> 4.8098281e+09

Sheet Sheet4
A3: Average of Sales | B3: Column Labels
A4: Row Labels | B4: 2014 | C4: 2015 | D4: Grand Total
A5: Burritos | B5: 768613.63 | C5: 700149.3 | D5: 732920.43
A6: Drinks | B6: 284764.44 | C6: 396137.1 | D6: 342827.48
A7: Kids menu | B7: 155642.02 | C7: 147399.85 | D7: 151345.05
A8: Tacos | B8: 622575.54 | C8: 598811.9 | D8: 610186.6
A9: Grand Total | B9: 457898.91 | C9: 460624.54 | D9: 459319.89

Sheet Sheet7
A3: Sum of Sales | B3: Column Labels
A4: Row Labels | B4: 2014 | C4: 2015 | D4: Grand Total
A5: Burritos | B5: 1.7240004e+09 | C5: 1.7104647e+09 | D5: 3.4344651e+09
A6: Drinks | B6: 6.3872664e+08 | C6: 9.6776295e+08 | D6: 1.6064896e+09
A7: Kids menu | B7: 3.4910505e+08 | C7: 3.6009784e+08 | D7: 7.0920289e+08
A8: Tacos | B8: 1.3964369e+09 | C8: 1.4628975e+09 | D8: 2.8593344e+09
A9: Grand Total | B9: 4.108269e+09 | C9: 4.501223e+09 | D9: 8.609492e+09
A15: Row Labels | B15: 2014 | C15: 2015 | D15: No of units sold per store in 2015
A16: Burritos | B16: 768613.63 | C16: 700149.3 | D16: =C16/'D. Current prices'!$E4 -> 71081.147
A17: Drinks | B17: 284764.44 | C17: 396137.1 | D17: =C17/'D. Current prices'!$E7 -> 117548.1
A18: Kids menu | B18: 155642.02 | C18: 147399.85 | D18: =C18/'D. Current prices'!$E6 -> 27863.866
A19: Tacos | B19: 622575.54 | C19: 598811.9 | D19: =C19/'D. Current prices'!$E5 -> 102712.16
A24: Row Labels | B24: 2014 | C24: 2015 | D24: no of units sold | E24: no of units sold per store
A25: Burritos | B25: 1.7240004e+09 | C25: 1.7104647e+09 | D25: =C25/'D. Current prices'!$E4 -> 1.7365124e+08 | E25: =D25/2443 -> 71081.147
A26: Drinks | B26: 6.3872664e+08 | C26: 9.6776295e+08 | D26: =C26/'D. Current prices'!$E7 -> 2.8717001e+08 | E26: =D26/2443 -> 117548.1
A27: Kids menu | B27: 3.4910505e+08 | C27: 3.6009784e+08 | D27: =C27/'D. Current prices'!$E6 -> 68071425 | E27: =D27/2443 -> 27863.866
A28: Tacos | B28: 1.3964369e+09 | C28: 1.4628975e+09 | D28: =C28/'D. Current prices'!$E5 -> 2.5092581e+08 | E28: =D28/2443 -> 102712.16

Sheet A. Sales by store
A1: Chiboodle, Inc.
A3: Financial_year | B3: Store_ID | C3: Product | D3: Sales | E3: Year opened | F3: new or old | G3: new or existing
A4: 2015 | B4: A0001 | C4: Burritos | D4: 870986.26 | E4: =INDEX('B. Store opening dates'!$B$5:$B$2448,MATCH('A. Sales by store'!B4,'B. Store opening dates'!$A$5:$A$2448,0)) -> 1994 | F4: =IF(A4 = 2015, IF(E4< 2015, "Old","New"),IF(E4 < 2014, "Old","New")) -> Old | G4: =IF(A4 = 2015, IF(E4< 2015, "Existing","New"),"Existing") -> Existing
A5: 2014 | B5: A0001 | C5: Burritos | D5: 963351.38 | E5: =INDEX('B. Store opening dates'!$B$5:$B$2448,MATCH('A. Sales by store'!B5,'B. Store opening dates'!$A$5:$A$2448,0)) -> 1994 | F5: =IF(A5 = 2015, IF(E5< 2015, "Old","New"),IF(E5 < 2014, "Old","New")) -> Old | G5: =IF(A5 = 2015, IF(E5< 2015, "Existing","New"),"Existing") -> Existing
A6: 2015 | B6: A0001 | C6: Drinks | D6: 461579.64 | E6: =INDEX('B. Store opening dates'!$B$5:$B$2448,MATCH('A. Sales by store'!B6,'B. Store opening dates'!$A$5:$A$2448,0)) -> 1994 | F6: =IF(A6 = 2015, IF(E6< 2015, "Old","New"),IF(E6 < 2014, "Old","New")) -> Old | G6: =IF(A6 = 2015, IF(E6< 2015, "Existing","New"),"Existing") -> Existing
A7: 2014 | B7: A0001 | C7: Drinks | D7: 320733.36 | E7: =INDEX('B. Store opening dates'!$B$5:$B$2448,MATCH('A. Sales by store'!B7,'B. Store opening dates'!$A$5:$A$2448,0)) -> 1994 | F7: =IF(A7 = 2015, IF(E7< 2015, "Old","New"),IF(E7 < 2014, "Old","New")) -> Old | G7: =IF(A7 = 2015, IF(E7< 2015, "Existing","New"),"Existing") -> Existing
A8: 2015 | B8: A0001 | C8: Kids menu | D8: 82194.81 | E8: =INDEX('B. Store opening dates'!$B$5:$B$2448,MATCH('A. Sales by store'!B8,'B. Store opening dates'!$A$5:$A$2448,0)) -> 1994 | F8: =IF(A8 = 2015, IF(E8< 2015, "Old","New"),IF(E8 < 2014, "Old","New")) -> Old | G8: =IF(A8 = 2015, IF(E8< 2015, "Existing","New"),"Existing") -> Existing
A9: 2014 | B9: A0001 | C9: Kids menu | D9: 86328.79 | E9: =INDEX('B. Store opening dates'!$B$5:$B$2448,MATCH('A. Sales by store'!B9,'B. Store opening dates'!$A$5:$A$2448,0)) -> 1994 | F9: =IF(A9 = 2015, IF(E9< 2015, "Old","New"),IF(E9 < 2014, "Old","New")) -> Old | G9: =IF(A9 = 2015, IF(E9< 2015, "Existing","New"),"Existing") -> Existing
A10: 2015 | B10: A0001 | C10: Tacos | D10: 602287.16 | E10: =INDEX('B. Store opening dates'!$B$5:$B$2448,MATCH('A. Sales by store'!B10,'B. Store opening dates'!$A$5:$A$2448,0)) -> 1994 | F10: =IF(A10 = 2015, IF(E10< 2015, "Old","New"),IF(E10 < 2014, "Old","New")) -> Old | G10: =IF(A10 = 2015, IF(E10< 2015, "Existing","New"),"Existing") -> Existing
A11: 2014 | B11: A0001 | C11: Tacos | D11: 627868.96 | E11: =INDEX('B. Store opening dates'!$B$5:$B$2448,MATCH('A. Sales by store'!B11,'B. Store opening dates'!$A$5:$A$2448,0)) -> 1994 | F11: =IF(A11 = 2015, IF(E11< 2015, "Old","New"),IF(E11 < 2014, "Old","New")) -> Old | G11: =IF(A11 = 2015, IF(E11< 2015, "Existing","New"),"Existing") -> Existing
A12: 2015 | B12: A0002 | C12: Burritos | D12: 698164.47 | E12: =INDEX('B. Store opening dates'!$B$5:$B$2448,MATCH('A. Sales by store'!B12,'B. Store opening dates'!$A$5:$A$2448,0)) -> 1995 | F12: =IF(A12 = 2015, IF(E12< 2015, "Old","New"),IF(E12 < 2014, "Old","New")) -> Old | G12: =IF(A12 = 2015, IF(E12< 2015, "Existing","New"),"Existing") -> Existing
A13: 2014 | B13: A0002 | C13: Burritos | D13: 772730.07 | E13: =INDEX('B. Store opening dates'!$B$5:$B$2448,MATCH('A. Sales by store'!B13,'B. Store opening dates'!$A$5:$A$2448,0)) -> 1995 | F13: =IF(A13 = 2015, IF(E13< 2015, "Old","New"),IF(E13 < 2014, "Old","New")) -> Old | G13: =IF(A13 = 2015, IF(E13< 2015, "Existing","New"),"Existing") -> Existing
A14: 2015 | B14: A0002 | C14: Drinks | D14: 390399.78 | E14: =INDEX('B. Store opening dates'!$B$5:$B$2448,MATCH('A. Sales by store'!B14,'B. Store opening dates'!$A$5:$A$2448,0)) -> 1995 | F14: =IF(A14 = 2015, IF(E14< 2015, "Old","New"),IF(E14 < 2014, "Old","New")) -> Old | G14: =IF(A14 = 2015, IF(E14< 2015, "Existing","New"),"Existing") -> Existing
A15: 2014 | B15: A0002 | C15: Drinks | D15: 283087.3 | E15: =INDEX('B. Store opening dates'!$B$5:$B$2448,MATCH('A. Sales by store'!B15,'B. Store opening dates'!$A$5:$A$2448,0)) -> 1995 | F15: =IF(A15 = 2015, IF(E15< 2015, "Old","New"),IF(E15 < 2014, "Old","New")) -> Old | G15: =IF(A15 = 2015, IF(E15< 2015, "Existing","New"),"Existing") -> Existing
... A18747: 2015 | B18747: A2443 | C18747: Tacos | D18747: 686093.91 | E18747: =INDEX('B. Store opening dates'!$B$5:$B$2448,MATCH('A. Sales by store'!B18747,'B. Store opening dates'!$A$5:$A$2448,0)) -> 2015 | F18747: =IF(A18747 = 2015, IF(E18747< 2015, "Old","New"),IF(E18747 < 2014, "Old","New")) -> New | G18747: =IF(A18747 = 2015, IF(E18747< 2015, "Existing","New"),"Existing") -> New

Sheet B. Store opening dates
A1: Chiboodle, Inc.
A3: Existing stores as of Dec 31, 2015 -- zip code and year of opening
A5: Store_ID | B5: Year_opened | C5: Zip_code
A6: A0001 | B6: 1994 | C6: 87105
A7: A0002 | B7: 1995 | C7: 87101
A8: A0003 | B8: 1996 | C8: 47141
A9: A0004 | B9: 1996 | C9: 87844
A10: A0005 | B10: 1996 | C10: 92091
A11: A0006 | B11: 1996 | C11: 33621
A12: A0007 | B12: 1996 | C12: 39559
A13: A0008 | B13: 1997 | C13: 30461
A14: A0009 | B14: 1997 | C14: 67610
A15: A0010 | B15: 1997 | C15: 721
A16: A0011 | B16: 1997 | C16: 67865
A17: A0012 | B17: 1997 | C17: 37704
... A2448: A2443 | B2448: 2015 | C2448: 3605

Sheet C. New locations planned
A1: Chiboodle, Inc.
E2: 2015 (actual) | F2: 2016 (expected) | G2: 2017 (expected) | H2: 2018 (expected) | I2: 2019 (expected)
D3: Number of new stores planned | E3: 200 | F3: 153 | G3: 101 | H3: 72 | I3: 62
D4: Number of stores at year-end | E4: 2443 | F4: =SUM(E4,F3) -> 2596 | G4: =SUM(F4,G3) -> 2697 | H4: =SUM(G4,H3) -> 2769 | I4: =SUM(H4,I3) -> 2831
D12: =2443-200 -> 2243

Sheet D. Current prices
A1: Chiboodle, Inc.
D3: Product | E3: Average Price
D4: Burritos | E4: 9.85
D5: Tacos | E5: 5.83
D6: Kids menu | E6: 5.29
D7: Drinks | E7: 3.37

Sheet E. Competitor salad prices
A1: Chiboodle, Inc.
D3: Restaurant | E3: Average price of salad
D4: Adoba | E4: 10.165617
D5: Trendy's | E5: 9.2593106
D6: Wanda Express | E6: 8.2897515
D7: Quick service chain 4 | E7: 8.0209457
D8: Quick service chain 5 | E8: 10.384588
D9: Trick-zila | E9: 9.4164409
D10: Trendy's | E10: 6.748079
D11: McDaisy's | E11: 6.0002037
D12: Mosi | E12: 7.7102309
D13: Chiboodle Average | E13: =AVERAGE(E4:E12) -> 8.4439074
D14: Chiboodle Top of range | E14: =MAX(E4:E12) -> 10.384588

Sheet F. Survey
A1: Chiboodle, Inc.
D3: Question asked, right after people check out at the counter:
D4: How would your purchase behavior change if Chiboodle offered salads on the menu?
E6: Item purchased by survey respondent
D7: Restaurant | E7: Burrito | F7: Taco | G7: Kids meal | H7: Drink
D8: I would buy a salad instead of today's purchase | E8: 0.08 | F8: 0 | G8: 0 | H8: 0
D9: I would buy a salad in addition to today's purchase | E9: 0 | F9: 0.23 | G9: 0 | H9: 0
D10: I would make no change to my purchase | E10: 0.92 | F10: 0.77 | G10: 1 | H10: 1

Sheet G. Adoption curves
A1: Chiboodle, Inc.
E2: % of Chiboodle locations serving new item
D3: Years after launch | E3: Sofritas | F3: Guacamole | G3: Corn salsa | H3: Salads
D4: 0 | E4: 0.18 | F4: 0.27 | G4: 0.05 | H4: =AVERAGE(E4:G4) -> 0.16666667
D5: 1 | E5: 0.3 | F5: 0.33 | G5: 0.2 | H5: =AVERAGE(E5:G5) -> 0.27666667
D6: 2 | E6: 0.53 | F6: 0.67 | G6: 0.44 | H6: =AVERAGE(E6:G6) -> 0.54666667
D7: 3 | E7: 0.8 | F7: 0.88 | G7: 0.73 | H7: =AVERAGE(E7:G7) -> 0.80333333
D8: 4 | E8: 0.96 | F8: 1 | G8: 0.88 | H8: =AVERAGE(E8:G8) -> 0.94666667
D9: 5 | E9: 0.99 | F9: 1 | G9: 0.92 | H9: =AVERAGE(E9:G9) -> 0.97
D11: When a new menu item is launched, not all restaurant locations start selling it on day 1. It can take a few years for it to penetrate nationwide.
